[
{
    "case_code": "2021022200034",
    "market_name": "豬肉攤",
    "addr": "新北市三重區安慶街339號",
    "business_week": "星期二，星期三，星期四，星期五，星期六，星期日",
    "context": "",
    "ValidDate": "2024/03/03 16:00:00",
    "Latitude": "25.067315",
    "Lontitude": "121.487841",
    "type": "販售",
    "badge_code": "D003793",
    "business_hours": "07:00",
    "business_hurs_end": "12:00",
    "last_edited_date": "2021/03/19 02:30:13"
  },
  {
    "case_code": "2021030500005",
    "market_name": "十金鵝傳統鵝肉店",
    "addr": "宜蘭縣羅東鎮中正南路114號",
    "business_week": "星期一，星期二，星期四，星期五，星期六，星期日",
    "context": "超好吃的鵝肉飯",
    "ValidDate": "2024/03/10 16:00:00",
    "Latitude": "24.670425",
    "Lontitude": "121.771328",
    "type": "餐飲",
    "badge_code": "D004055",
    "business_hours": "11:00",
    "business_hurs_end": "21:00",
    "last_edited_date": "2021/03/17 05:30:15"
  }
]